pygenfsm/__init__.py
pygenfsm/fsm.py
pygenfsm/py.typed
pygenfsm-1.0.1.dist-info/METADATA
pygenfsm-1.0.1.dist-info/WHEEL
pygenfsm-1.0.1.dist-info/licenses/LICENSE
pygenfsm-1.0.1.dist-info/RECORD
