Metadata-Version: 2.4
Name: pygenfsm
Version: 1.0.1
Summary: A minimal, clean, typed and async-native FSM (Finite State Machine) implementation inspired by Erlang's gen_fsm
Project-URL: Homepage, https://github.com/serialx/pygenfsm
Project-URL: Repository, https://github.com/serialx/pygenfsm
Project-URL: Issues, https://github.com/serialx/pygenfsm/issues
Author-email: SerialX <serialx@serialx.net>
Maintainer-email: SerialX <serialx@serialx.net>
License-Expression: MIT
License-File: LICENSE
Keywords: async,asyncio,automation,erlang,event-driven,finite-state-machine,fsm,gen_fsm,state-machine,state-management,typed,workflow
Classifier: Development Status :: 3 - Alpha
Classifier: Intended Audience :: Developers
Classifier: License :: OSI Approved :: MIT License
Classifier: Programming Language :: Python :: 3
Classifier: Programming Language :: Python :: 3.11
Classifier: Programming Language :: Python :: 3.12
Classifier: Topic :: Software Development :: Libraries
Classifier: Typing :: Typed
Requires-Python: >=3.11
